birdwell/utils/__init__.py
birdwell/utils/items.py
birdwell/utils/strings.py
birdwell/utils/thread.py
birdwell/utils/time.py
birdwell/utils/trigram.py
birdwell_utils-2.0.1rc14.dev2.dist-info/LICENSE
birdwell_utils-2.0.1rc14.dev2.dist-info/METADATA
birdwell_utils-2.0.1rc14.dev2.dist-info/WHEEL
birdwell_utils-2.0.1rc14.dev2.dist-info/top_level.txt
birdwell_utils-2.0.1rc14.dev2.dist-info/RECORD
