Metadata-Version: 2.1
Name: birdwell-utils
Version: 2.0.1rc14.dev2
Summary: misc utils submodule of the birdwell namespace package
Author-email: jcbirdwell <jcbirdwell@gmail.com>
License: MIT License
Requires-Python: >=3.12
License-File: LICENSE
